awc_cli/__init__.py
awc_cli/__main__.py
awc_cli/config.py
awc_cli/py.typed
awc_cli/repl.py
awc_cli/util.py
awc_cli/cmd/__init__.py
awc_cli/cmd/admin_cmds.py
awc_cli/cmd/cmds.py
awc_cli/cmd/mgr.py
awc_cli/cmd/user_cmds.py
awc_cli-1.4.0.dist-info/LICENSE
awc_cli-1.4.0.dist-info/METADATA
awc_cli-1.4.0.dist-info/WHEEL
awc_cli-1.4.0.dist-info/entry_points.txt
awc_cli-1.4.0.dist-info/top_level.txt
awc_cli-1.4.0.dist-info/zip-safe
awc_cli-1.4.0.dist-info/RECORD
