Metadata-Version: 2.1
Name: awc-cli
Version: 1.4.0
Summary: cli for https://server.ari-web.xyz/
Home-page: https://ari-web.xyz/gh/awc-cli
Author: Ari Archer
Author-email: ari.web.xyz@gmail.com
License: GPLv3+
Keywords: http,comments,api,https,awc
Classifier: Development Status :: 5 - Production/Stable
Classifier: Environment :: Console
Classifier: Intended Audience :: End Users/Desktop
Classifier: License :: OSI Approved :: GNU General Public License v3 or later (GPLv3+)
Classifier: Operating System :: OS Independent
Classifier: Programming Language :: Python :: 3
Classifier: Programming Language :: Python :: 3.8
Classifier: Programming Language :: Python :: 3.9
Classifier: Programming Language :: Python :: 3.10
Classifier: Programming Language :: Python :: 3.11
Classifier: Programming Language :: Python :: 3.12
Classifier: Topic :: Internet :: WWW/HTTP
Classifier: Typing :: Typed
License-File: LICENSE
Requires-Dist: awc (>=3.2.0)
Requires-Dist: sqlparse
Requires-Dist: lxml
